monkeyrun/__init__.py
monkeyrun/base.py
monkeyrun/base_decorator.py
monkeyrun/checkfunc.py
monkeyrun/getinfo.py
monkeyrun/mod_database.py
monkeyrun/mod_logger.py
monkeyrun/monkeyLib.py
monkeyrun/run.py
monkeyrun/selectXml.py
monkeyrun/test.py
monkeyrun-0.0.6.dist-info/LICENSE
monkeyrun-0.0.6.dist-info/METADATA
monkeyrun-0.0.6.dist-info/WHEEL
monkeyrun-0.0.6.dist-info/top_level.txt
monkeyrun-0.0.6.dist-info/RECORD
