Metadata-Version: 2.1
Name: monkeyrun
Version: 0.0.6
Summary: MonkeyRunnerTestCase
Home-page: https://github.com/pypa/sampleproject
Author: wanghan
Author-email: wanghan0406@autohome.com.cn
License: UNKNOWN
Platform: UNKNOWN
Classifier: Programming Language :: Python :: 3
Classifier: License :: OSI Approved :: MIT License
Classifier: Operating System :: OS Independent
